wallpaper_fetcher/__init__.py
wallpaper_fetcher/autostart.py
wallpaper_fetcher/fetcher.py
wallpaper_fetcher/logger.py
wallpaper_fetcher/set_wallpaper.py
wallpaper_fetcher/wallpaper.py
wallpaper_fetcher/wallpaper_rotator.py
wallpaper_fetcher-0.2.6.dist-info/METADATA
wallpaper_fetcher-0.2.6.dist-info/WHEEL
wallpaper_fetcher-0.2.6.dist-info/entry_points.txt
wallpaper_fetcher-0.2.6.dist-info/RECORD
