Metadata-Version: 2.3
Name: wallpaper_fetcher
Version: 0.2.6
Summary: A python script to automatically fetch and apply the daily Bing wallpaper on Linux, Mac or Windows.
License: MIT
Author: Johannes Gundlach
Author-email: 24914225+Johannes11833@users.noreply.github.com
Requires-Python: >=3.9,<3.14
Classifier: License :: OSI Approved :: MIT License
Classifier: Programming Language :: Python :: 3
Classifier: Programming Language :: Python :: 3.9
Classifier: Programming Language :: Python :: 3.10
Classifier: Programming Language :: Python :: 3.11
Classifier: Programming Language :: Python :: 3.12
Classifier: Programming Language :: Python :: 3.13
Requires-Dist: requests (>=2.32.3,<3.0.0)
Requires-Dist: rich (>=13.9.4,<14.0.0)
Project-URL: repository, https://github.com/Johannes11833/BingWallpaperFetcher
